{
"skeleton": { "hash": "eqyL15mGdhv4vfvTb8QZCe8YnHI", "spine": "2.1.27", "width": 0, "height": 0, "images": "./../../pngs/animation/ui/" },
"bones": [
	{ "name": "root" },
	{ "name": "code_weizhi", "parent": "root", "x": 62.99, "y": -67.86 },
	{ "name": "refer", "parent": "root" }
],
"slots": [
	{ "name": "refer", "bone": "refer" },
	{ "name": "code_weizhi", "bone": "code_weizhi" }
],
"animations": {
	"animation": {},
	"animation2": {},
	"blue": {},
	"green": {},
	"orange": {},
	"purple": {},
	"red": {},
	"yellow": {}
}
}