{"skeleton":{"hash":"Lqq5ljr20NfMd7rD37ZUHQIcGvM","spine":"2.1.27","width":0,"height":0,"images":"./../../pngs/fx/"},"bones":[{"name":"root"},{"name":"down","parent":"root","scaleX":1.05,"scaleY":1.05},{"name":"diyun","parent":"down"},{"name":"xiamian","parent":"down","scaleX":2,"scaleY":2}],"slots":[{"name":"xiamian","bone":"xiamian"},{"name":"diyun","bone":"diyun","color":"ff8300ff","blend":"additive"}],"skins":{"default":{"diyun":{"common/diyun":{"width":128,"height":128}},"xiamian":{"fx_1421/xiamian_00000":{"width":126,"height":53},"fx_1421/xiamian_00001":{"width":126,"height":53},"fx_1421/xiamian_00003":{"width":126,"height":53},"fx_1421/xiamian_00004":{"width":126,"height":53},"fx_1421/xiamian_00006":{"width":126,"height":53},"fx_1421/xiamian_00007":{"width":126,"height":53},"fx_1421/xiamian_00009":{"width":126,"height":53},"fx_1421/xiamian_00010":{"width":126,"height":53},"fx_1421/xiamian_00012":{"width":126,"height":53},"fx_1421/xiamian_00013":{"width":126,"height":53},"fx_1421/xiamian_00015":{"width":126,"height":53},"fx_1421/xiamian_00016":{"width":126,"height":53},"fx_1421/xiamian_00018":{"width":126,"height":53},"fx_1421/xiamian_00019":{"width":126,"height":53}}}},"events":{"hit":{}},"animations":{"animation":{"slots":{"diyun":{"attachment":[{"time":0.5333,"name":"common/diyun"}],"color":[{"time":0.8333,"color":"ff8300ff"},{"time":1.2666,"color":"ff830000"}]},"xiamian":{"attachment":[{"time":0.5333,"name":"fx_1421/xiamian_00000"},{"time":0.5666,"name":"fx_1421/xiamian_00001"},{"time":0.6333,"name":"fx_1421/xiamian_00003"},{"time":0.6666,"name":"fx_1421/xiamian_00004"},{"time":0.7333,"name":"fx_1421/xiamian_00006"},{"time":0.7666,"name":"fx_1421/xiamian_00007"},{"time":0.8333,"name":"fx_1421/xiamian_00009"},{"time":0.8666,"name":"fx_1421/xiamian_00010"},{"time":0.9333,"name":"fx_1421/xiamian_00012"},{"time":0.9666,"name":"fx_1421/xiamian_00013"},{"time":1.0333,"name":"fx_1421/xiamian_00015"},{"time":1.0666,"name":"fx_1421/xiamian_00016"},{"time":1.1333,"name":"fx_1421/xiamian_00018"},{"time":1.1666,"name":"fx_1421/xiamian_00019"},{"time":1.2666,"name":null}],"color":[{"time":1.1666,"color":"ffffffff"},{"time":1.2666,"color":"ffffff00"}]}},"bones":{"diyun":{"scale":[{"time":0.5333,"x":1.41,"y":0.64},{"time":0.6,"x":3.25,"y":1.43}]}},"events":[{"time":0.5333,"name":"hit"}]}}}